{
  "users": [
    {
      "email": "maxime@1",
      "password": "$2a$10$h6e6crRHkJ4UgzftUC7Sze/2ZIxYJ/GDBN23utY5tG/Rhj..BxIy2",
      "id": 1,
      "username": "maxime"
    }
  ],
  "projects": [
    {
      "id": 1,
      "title": "Projet 1",
      "description": "Ceci est la description du premier projet. Il n'a ni date de début, ni date de fin (pour l'instant).",
      "startDate": "2024-04-26",
      "endDate": "2024-04-29"
    },
    {
      "id": 2,
      "title": "Projet 2 : Aenean ornare velit lacus",
      "description": "Je suis le projet \"Aenean ornare velit lacus\". Je n'ai pas encore de date de début, ni de date de fin (mais ça viendra).",
      "startDate": "",
      "endDate": ""
    }
  ]
}